redis_timeseries.py
redis_timeseries-0.1.9.dist-info/LICENSE
redis_timeseries-0.1.9.dist-info/METADATA
redis_timeseries-0.1.9.dist-info/WHEEL
redis_timeseries-0.1.9.dist-info/top_level.txt
redis_timeseries-0.1.9.dist-info/RECORD
