Metadata-Version: 2.1
Name: redis-timeseries
Version: 0.1.9
Summary: Timeseries API built on top of Redis
Home-page: https://github.com/ryananguiano/python-redis-timeseries
Author: Ryan Anguiano
Author-email: ryan.anguiano@gmail.com
License: MIT license
Keywords: redis_timeseries
Platform: UNKNOWN
Classifier: Development Status :: 4 - Beta
Classifier: Intended Audience :: Developers
Classifier: License :: OSI Approved :: MIT License
Classifier: Natural Language :: English
Classifier: Programming Language :: Python :: 2
Classifier: Programming Language :: Python :: 2.7
Classifier: Programming Language :: Python :: 3
Classifier: Programming Language :: Python :: 3.4
Classifier: Programming Language :: Python :: 3.5
Classifier: Programming Language :: Python :: 3.6
Requires-Dist: redis
